[
  {
    "title": "Quarto potere",
    "tmdb_id": 15
  },
  {
    "title": "Il settimo sigillo",
    "tmdb_id": 490
  },
  {
    "title": "La nascita di una nazione",
    "tmdb_id": 618
  },
  {
    "title": "Aleksandr Nevskij",
    "tmdb_id": 10235
  },
  {
    "title": "I sette samurai",
    "tmdb_id": 346
  },
  {
    "title": "Psycho",
    "tmdb_id": 539
  },
  {
    "title": "Tempi moderni",
    "tmdb_id": 3082
  },
  {
    "title": "Rocco e i suoi fratelli",
    "tmdb_id": 8422
  },
  {
    "title": "L'infernale Quinlan",
    "tmdb_id": 1480
  },
  {
    "title": "La Passione di Giovanna d'Arco",
    "tmdb_id": 780
  },
  {
    "title": "La donna che visse due volte",
    "tmdb_id": 426
  },
  {
    "title": "Il buono, il brutto, il cattivo",
    "tmdb_id": 429
  },
  {
    "title": "Nosferatu il vampiro",
    "tmdb_id": 653
  },
  {
    "title": "C'era una volta il West",
    "tmdb_id": 335
  },
  {
    "title": "Il grande dittatore",
    "tmdb_id": 914
  },
  {
    "title": "Il gabinetto del Dottor Caligari",
    "tmdb_id": 109133
  },
  {
    "title": "La parola ai giurati",
    "tmdb_id": 389
  },
  {
    "title": "M, il mostro di Dusseldorf",
    "tmdb_id": 832
  },
  {
    "title": "Eva contro Eva",
    "tmdb_id": 705
  },
  {
    "title": "La finestra sul cortile",
    "tmdb_id": 567
  },
  {
    "title": "Metropolis",
    "tmdb_id": 19
  },
  {
    "title": "Viale del tramonto",
    "tmdb_id": 599
  },
  {
    "title": "Luci della città",
    "tmdb_id": 901
  },
  {
    "title": "Ossessione",
    "tmdb_id": 5155
  },
  {
    "title": "Per qualche dollaro in più",
    "tmdb_id": 938
  },
  {
    "title": "Aurora",
    "tmdb_id": 133764
  },
  {
    "title": "Rashomon",
    "tmdb_id": 548
  },
  {
    "title": "Per un pugno di dollari",
    "tmdb_id": 391
  },
  {
    "title": "Roma città aperta",
    "tmdb_id": 307
  },
  {
    "title": "I 400 colpi",
    "tmdb_id": 147
  },
  {
    "title": "Il processo",
    "tmdb_id": 548755
  },
  {
    "title": "Vogliamo vivere",
    "tmdb_id": 198
  },
  {
    "title": "2001: Odissea nello spazio",
    "tmdb_id": 62
  },
  {
    "title": "I soliti ignoti",
    "tmdb_id": 24382
  },
  {
    "title": "Ladri di biciclette",
    "tmdb_id": 5156
  },
  {
    "title": "Femmine folli",
    "tmdb_id": 35227
  },
  {
    "title": "Mancia competente",
    "tmdb_id": 195
  },
  {
    "title": "Un dollaro d'onore",
    "tmdb_id": 301
  },
  {
    "title": "La sfida del samurai",
    "tmdb_id": 11878
  },
  {
    "title": "La corazzata Potëmkin",
    "tmdb_id": 643
  },
  {
    "title": "Il dottor Stranamore",
    "tmdb_id": 935
  },
  {
    "title": "La grande guerra",
    "tmdb_id": 55823
  },
  {
    "title": "Il testamento di Orfeo",
    "tmdb_id": 36878
  },
  {
    "title": "Susanna",
    "tmdb_id": 920597
  },
  {
    "title": "Napoleone",
    "tmdb_id": 619380
  },
  {
    "title": "Fino all'ultimo respiro",
    "tmdb_id": 269
  },
  {
    "title": "Il posto delle fragole",
    "tmdb_id": 614
  },
  {
    "title": "Il sorpasso",
    "tmdb_id": 24188
  },
  {
    "title": "L'Âge d'or",
    "tmdb_id": 558853
  },
  {
    "title": "Uccellacci e uccellini",
    "tmdb_id": 33954
  },
  {
    "title": "Scarface - Lo sfregiato",
    "tmdb_id": 877
  },
  {
    "title": "La caduta degli dei",
    "tmdb_id": 41876
  },
  {
    "title": "La morte corre sul fiume",
    "tmdb_id": 3112
  },
  {
    "title": "Sciuscià",
    "tmdb_id": 43469
  },
  {
    "title": "Ninotchka",
    "tmdb_id": 1859
  },
  {
    "title": "I migliori anni della nostra vita",
    "tmdb_id": 887
  },
  {
    "title": "Le sang d'un poète",
    "tmdb_id": 36877
  },
  {
    "title": "Il mucchio selvaggio",
    "tmdb_id": 576
  },
  {
    "title": "Il monello",
    "tmdb_id": 694281
  },
  {
    "title": "8½",
    "tmdb_id": 1326106
  },
  {
    "title": "Paisà",
    "tmdb_id": 8429
  },
  {
    "title": "La Bella e la Bestia",
    "tmdb_id": 321612
  },
  {
    "title": "La guerra lampo dei fratelli Marx",
    "tmdb_id": 3063
  },
  {
    "title": "Gli uccelli",
    "tmdb_id": 587032
  },
  {
    "title": "L'avventura",
    "tmdb_id": 5165
  },
  {
    "title": "Senso",
    "tmdb_id": 43195
  },
  {
    "title": "Trono di sangue",
    "tmdb_id": 3777
  },
  {
    "title": "Fronte del porto",
    "tmdb_id": 654
  },
  {
    "title": "Orizzonti di gloria",
    "tmdb_id": 975
  },
  {
    "title": "L'angelo sterminatore",
    "tmdb_id": 29264
  },
  {
    "title": "Sentieri selvaggi",
    "tmdb_id": 3114
  },
  {
    "title": "Zero in condotta",
    "tmdb_id": 44494
  },
  {
    "title": "Operazione sottoveste",
    "tmdb_id": 9660
  },
  {
    "title": "Intrigo internazionale",
    "tmdb_id": 28661
  },
  {
    "title": "A me la libertà",
    "tmdb_id": 31514
  },
  {
    "title": "Gli invasati",
    "tmdb_id": 11772
  },
  {
    "title": "Casablanca",
    "tmdb_id": 1386711
  },
  {
    "title": "L'appartamento",
    "tmdb_id": 284
  },
  {
    "title": "L'Angelo azzurro",
    "tmdb_id": 228
  },
  {
    "title": "Rapina a mano armata",
    "tmdb_id": 247
  },
  {
    "title": "I racconti della pallida luna d'agosto",
    "tmdb_id": 14696
  },
  {
    "title": "Il bandito delle 11",
    "tmdb_id": 2786
  },
  {
    "title": "La febbre dell'oro",
    "tmdb_id": 962
  },
  {
    "title": "Hiroshima mon amour",
    "tmdb_id": 5544
  },
  {
    "title": "Un tram che si chiama desiderio",
    "tmdb_id": 702
  },
  {
    "title": "Lo spione",
    "tmdb_id": 20778
  },
  {
    "title": "I figli della violenza",
    "tmdb_id": 800
  },
  {
    "title": "La fontana della vergine",
    "tmdb_id": 11656
  },
  {
    "title": "I 47 ronin ribelli",
    "tmdb_id": 45978
  },
  {
    "title": "Inizio d'estate",
    "tmdb_id": 132318
  },
  {
    "title": "Questa terra è mia",
    "tmdb_id": 433249
  },
  {
    "title": "La vita di Òharu donna galante",
    "tmdb_id": 43364
  },
  {
    "title": "Tarda primavera",
    "tmdb_id": 20530
  },
  {
    "title": "Il gusto del sakè",
    "tmdb_id": 50759
  },
  {
    "title": "Viaggio a Tokyo",
    "tmdb_id": 18148
  },
  {
    "title": "La splendida spada di Bijomaru",
    "tmdb_id": 205649
  },
  {
    "title": "L'angelo del male",
    "tmdb_id": 531309
  },
  {
    "title": "Frank Costello faccia d'angelo",
    "tmdb_id": 5511
  },
  {
    "title": "Kwaidan",
    "tmdb_id": 1058062
  },
  {
    "title": "Jules e Jim",
    "tmdb_id": 1628
  },
  {
    "title": "Il padrino",
    "tmdb_id": 238
  },
  {
    "title": "Barry Lyndon",
    "tmdb_id": 3175
  },
  {
    "title": "Taxi Driver",
    "tmdb_id": 437068
  },
  {
    "title": "Sussurri e grida",
    "tmdb_id": 10238
  },
  {
    "title": "Apocalypse Now",
    "tmdb_id": 28
  },
  {
    "title": "Il padrino - Parte seconda",
    "tmdb_id": 240
  },
  {
    "title": "Arancia meccanica",
    "tmdb_id": 185
  },
  {
    "title": "Il cacciatore",
    "tmdb_id": 539972
  },
  {
    "title": "I senza nome",
    "tmdb_id": 11657
  },
  {
    "title": "Qualcuno volò sul nido del cuculo",
    "tmdb_id": 510
  },
  {
    "title": "Stalker",
    "tmdb_id": 1004130
  },
  {
    "title": "Led Zeppelin: The Song Remains the Same",
    "tmdb_id": 40440
  },
  {
    "title": "Nashville",
    "tmdb_id": 3121
  },
  {
    "title": "Quell'oscuro oggetto del desiderio",
    "tmdb_id": 5781
  },
  {
    "title": "Giù la testa",
    "tmdb_id": 336
  },
  {
    "title": "Il lungo addio",
    "tmdb_id": 1847
  },
  {
    "title": "Solaris",
    "tmdb_id": 2103
  },
  {
    "title": "C'eravamo tanto amati",
    "tmdb_id": 42269
  },
  {
    "title": "Frankenstein Junior",
    "tmdb_id": 3034
  },
  {
    "title": "La stangata",
    "tmdb_id": 9277
  },
  {
    "title": "In nome del popolo italiano",
    "tmdb_id": 65573
  },
  {
    "title": "Il fascino discreto della borghesia",
    "tmdb_id": 4593
  },
  {
    "title": "Profumo di donna",
    "tmdb_id": 47848
  },
  {
    "title": "Indagine su un cittadino al di sopra di ogni sospetto",
    "tmdb_id": 26451
  },
  {
    "title": "Morte a Venezia",
    "tmdb_id": 6619
  },
  {
    "title": "L'esorcista",
    "tmdb_id": 758323
  },
  {
    "title": "Il caso Mattei",
    "tmdb_id": 62382
  },
  {
    "title": "L'albero degli zoccoli",
    "tmdb_id": 31542
  },
  {
    "title": "Harold e Maude",
    "tmdb_id": 343
  },
  {
    "title": "Pat Garrett e Billy the Kid",
    "tmdb_id": 11577
  },
  {
    "title": "Alien",
    "tmdb_id": 348
  },
  {
    "title": "La rabbia giovane",
    "tmdb_id": 3133
  },
  {
    "title": "Il fiore delle mille e una notte",
    "tmdb_id": 47406
  },
  {
    "title": "Ziggy Stardust and the Spiders from Mars",
    "tmdb_id": 34759
  },
  {
    "title": "L'enigma di Kaspar Hauser",
    "tmdb_id": 11710
  },
  {
    "title": "Aguirre, furore di Dio",
    "tmdb_id": 2000
  },
  {
    "title": "Nosferatu, principe della notte",
    "tmdb_id": 6404
  },
  {
    "title": "Sacco e Vanzetti",
    "tmdb_id": 48211
  },
  {
    "title": "I guerrieri della notte",
    "tmdb_id": 11474
  },
  {
    "title": "La prima notte di quiete",
    "tmdb_id": 47251
  },
  {
    "title": "Effetto notte",
    "tmdb_id": 1675
  },
  {
    "title": "Oltre il giardino",
    "tmdb_id": 10322
  },
  {
    "title": "Il texano dagli occhi di ghiaccio",
    "tmdb_id": 10747
  },
  {
    "title": "La conversazione",
    "tmdb_id": 592
  },
  {
    "title": "Una giornata particolare",
    "tmdb_id": 42229
  },
  {
    "title": "Corvo Rosso non avrai il mio scalpo",
    "tmdb_id": 11943
  },
  {
    "title": "Padre padrone",
    "tmdb_id": 42225
  },
  {
    "title": "Comma 22",
    "tmdb_id": 10364
  },
  {
    "title": "I tre giorni del condor",
    "tmdb_id": 11963
  },
  {
    "title": "La classe operaia va in paradiso",
    "tmdb_id": 56231
  },
  {
    "title": "Quel pomeriggio di un giorno da cani",
    "tmdb_id": 968
  },
  {
    "title": "Tristana",
    "tmdb_id": 35838
  },
  {
    "title": "Tutti gli uomini del presidente",
    "tmdb_id": 891
  },
  {
    "title": "Lo straniero senza nome",
    "tmdb_id": 11901
  },
  {
    "title": "Il tamburo di latta",
    "tmdb_id": 659
  },
  {
    "title": "L'ultimo spettacolo",
    "tmdb_id": 438303
  },
  {
    "title": "Cinque pezzi facili",
    "tmdb_id": 26617
  },
  {
    "title": "La montagna sacra",
    "tmdb_id": 8327
  },
  {
    "title": "Chinatown",
    "tmdb_id": 829
  },
  {
    "title": "La ballata di Stroszek",
    "tmdb_id": 11698
  },
  {
    "title": "Quinto potere",
    "tmdb_id": 199779
  },
  {
    "title": "L'eroe della strada",
    "tmdb_id": 517026
  },
  {
    "title": "Picnic ad Hanging Rock",
    "tmdb_id": 11020
  },
  {
    "title": "Piccolo grande uomo",
    "tmdb_id": 11040
  },
  {
    "title": "Profondo Rosso",
    "tmdb_id": 20126
  },
  {
    "title": "La paura mangia l'anima",
    "tmdb_id": 216
  },
  {
    "title": "Woyzeck",
    "tmdb_id": 48199
  },
  {
    "title": "La grande abbuffata",
    "tmdb_id": 10102
  },
  {
    "title": "Il diritto del più forte",
    "tmdb_id": 42254
  },
  {
    "title": "Fuoco di paglia",
    "tmdb_id": 290482
  },
  {
    "title": "L'uomo che amava le donne",
    "tmdb_id": 1421
  },
  {
    "title": "Il giorno dello sciacallo",
    "tmdb_id": 4909
  },
  {
    "title": "Il ragazzo selvaggio",
    "tmdb_id": 1627
  },
  {
    "title": "Adele H., una storia d'amore",
    "tmdb_id": 1829
  },
  {
    "title": "Il maratoneta",
    "tmdb_id": 580725
  },
  {
    "title": "Un tranquillo week-end di paura",
    "tmdb_id": 10669
  },
  {
    "title": "Un mercoledì da leoni",
    "tmdb_id": 18387
  },
  {
    "title": "Lo chiamavano Trinità",
    "tmdb_id": 9394
  },
  {
    "title": "Fuga da Alcatraz",
    "tmdb_id": 10734
  },
  {
    "title": "Distretto 13: le brigate della morte",
    "tmdb_id": 17814
  },
  {
    "title": "Cane di paglia",
    "tmdb_id": 994
  },
  {
    "title": "Zabriskie Point",
    "tmdb_id": 1107404
  },
  {
    "title": "Ispettore Callaghan: il caso Scorpio è tuo",
    "tmdb_id": 984
  },
  {
    "title": "Una calibro 20 per lo specialista",
    "tmdb_id": 8348
  },
  {
    "title": "Quell'ultimo ponte",
    "tmdb_id": 5902
  },
  {
    "title": "Il decameron",
    "tmdb_id": 33583
  },
  {
    "title": "Le due sorelle",
    "tmdb_id": 445119
  },
  {
    "title": "Il matrimonio di Maria Braun",
    "tmdb_id": 661
  },
  {
    "title": "MASH",
    "tmdb_id": 651
  },
  {
    "title": "Una 44 Magnum per l'ispettore Callaghan",
    "tmdb_id": 10648
  },
  {
    "title": "Il giardino dei Finzi Contini",
    "tmdb_id": 4789
  },
  {
    "title": "La collina dei conigli",
    "tmdb_id": 11837
  },
  {
    "title": "El Topo",
    "tmdb_id": 13041
  },
  {
    "title": "Il braccio violento della legge",
    "tmdb_id": 1051
  },
  {
    "title": "Novecento",
    "tmdb_id": 3870
  },
  {
    "title": "Brian di Nazareth",
    "tmdb_id": 583
  },
  {
    "title": "I ragazzi venuti dal Brasile",
    "tmdb_id": 16241
  },
  {
    "title": "Il giustiziere della notte",
    "tmdb_id": 395990
  },
  {
    "title": "Jesus Christ Superstar",
    "tmdb_id": 12545
  },
  {
    "title": "Halloween - La notte delle streghe",
    "tmdb_id": 948
  },
  {
    "title": "C'era una volta in America",
    "tmdb_id": 10620
  },
  {
    "title": "Toro scatenato",
    "tmdb_id": 1578
  },
  {
    "title": "Full Metal Jacket",
    "tmdb_id": 600
  },
  {
    "title": "Fanny e Alexander",
    "tmdb_id": 114034
  },
  {
    "title": "Ran",
    "tmdb_id": 635736
  },
  {
    "title": "Shining",
    "tmdb_id": 1441396
  },
  {
    "title": "Kagemusha - L'ombra del guerriero",
    "tmdb_id": 11953
  },
  {
    "title": "Scarface",
    "tmdb_id": 111
  },
  {
    "title": "I cancelli del cielo",
    "tmdb_id": 10935
  },
  {
    "title": "Brazil",
    "tmdb_id": 68
  },
  {
    "title": "1997: Fuga da New York",
    "tmdb_id": 1103
  },
  {
    "title": "Terminator",
    "tmdb_id": 280
  },
  {
    "title": "Brubaker",
    "tmdb_id": 1623
  },
  {
    "title": "Gli intoccabili",
    "tmdb_id": 45138
  },
  {
    "title": "Bird",
    "tmdb_id": 1128752
  },
  {
    "title": "'Round Midnight - A mezzanotte circa",
    "tmdb_id": 14670
  },
  {
    "title": "Gente comune",
    "tmdb_id": 16619
  },
  {
    "title": "Veronika Voss",
    "tmdb_id": 2262
  },
  {
    "title": "Fitzcarraldo",
    "tmdb_id": 9343
  },
  {
    "title": "The Blues Brothers",
    "tmdb_id": 525
  },
  {
    "title": "La casa 2",
    "tmdb_id": 765
  },
  {
    "title": "L'ultimo metrò",
    "tmdb_id": 1716
  },
  {
    "title": "Un amore di Swann",
    "tmdb_id": 119623
  },
  {
    "title": "Aliens - Scontro finale",
    "tmdb_id": 679
  },
  {
    "title": "Blade Runner",
    "tmdb_id": 78
  },
  {
    "title": "Il cavaliere pallido",
    "tmdb_id": 8879
  },
  {
    "title": "L'attimo fuggente",
    "tmdb_id": 207
  },
  {
    "title": "Morte di un commesso viaggiatore",
    "tmdb_id": 12615
  },
  {
    "title": "Omicidio a luci rosse",
    "tmdb_id": 11507
  },
  {
    "title": "Vestito per uccidere",
    "tmdb_id": 11033
  },
  {
    "title": "Il mio piede sinistro",
    "tmdb_id": 10161
  },
  {
    "title": "La casa",
    "tmdb_id": 648990
  },
  {
    "title": "Platoon",
    "tmdb_id": 792
  },
  {
    "title": "Monty Python: il senso della vita",
    "tmdb_id": 4543
  },
  {
    "title": "La cosa",
    "tmdb_id": 168735
  },
  {
    "title": "Ricomincio da tre",
    "tmdb_id": 13386
  },
  {
    "title": "Il verdetto",
    "tmdb_id": 41590
  },
  {
    "title": "Fog",
    "tmdb_id": 517929
  },
  {
    "title": "Santa Sangre",
    "tmdb_id": 19236
  },
  {
    "title": "Amadeus",
    "tmdb_id": 279
  },
  {
    "title": "Blow Out",
    "tmdb_id": 11644
  },
  {
    "title": "Scusate il ritardo",
    "tmdb_id": 56784
  },
  {
    "title": "Inseparabili",
    "tmdb_id": 26908
  },
  {
    "title": "Rusty il selvaggio",
    "tmdb_id": 232
  },
  {
    "title": "Ritorno al futuro",
    "tmdb_id": 105
  },
  {
    "title": "Inferno",
    "tmdb_id": 207932
  },
  {
    "title": "Gli anni spezzati",
    "tmdb_id": 248939
  },
  {
    "title": "L'impero colpisce ancora",
    "tmdb_id": 1891
  },
  {
    "title": "Reds",
    "tmdb_id": 18254
  },
  {
    "title": "Coraggio... fatti ammazzare",
    "tmdb_id": 10650
  },
  {
    "title": "Vittime di guerra",
    "tmdb_id": 10142
  },
  {
    "title": "Signori, il delitto è servito",
    "tmdb_id": 15196
  },
  {
    "title": "Stati di allucinazione",
    "tmdb_id": 11542
  },
  {
    "title": "Akira",
    "tmdb_id": 149
  },
  {
    "title": "Possession",
    "tmdb_id": 30072
  },
  {
    "title": "I Goonies",
    "tmdb_id": 9340
  },
  {
    "title": "Vivere e morire a Los Angeles",
    "tmdb_id": 9846
  },
  {
    "title": "Non ci resta che piangere",
    "tmdb_id": 27670
  },
  {
    "title": "Il signore del male",
    "tmdb_id": 8852
  },
  {
    "title": "Piramide di paura",
    "tmdb_id": 11904
  },
  {
    "title": "Il cielo sopra Berlino",
    "tmdb_id": 144
  },
  {
    "title": "E.T. L'Extraterrestre",
    "tmdb_id": 601
  },
  {
    "title": "Conan il barbaro",
    "tmdb_id": 9387
  },
  {
    "title": "I cavalieri dalle lunghe ombre",
    "tmdb_id": 14729
  },
  {
    "title": "Il grande freddo",
    "tmdb_id": 402001
  },
  {
    "title": "Victor Victoria",
    "tmdb_id": 12614
  },
  {
    "title": "Nightmare - Dal profondo della notte",
    "tmdb_id": 377
  },
  {
    "title": "Pink Floyd The Wall",
    "tmdb_id": 79708
  },
  {
    "title": "Amici miei atto II",
    "tmdb_id": 24161
  },
  {
    "title": "Nato il quattro luglio",
    "tmdb_id": 2604
  },
  {
    "title": "Marrakech Express",
    "tmdb_id": 41583
  },
  {
    "title": "Grosso guaio a Chinatown",
    "tmdb_id": 6978
  },
  {
    "title": "Il giorno degli zombi",
    "tmdb_id": 8408
  },
  {
    "title": "Manhunter - Frammenti di un omicidio",
    "tmdb_id": 11454
  },
  {
    "title": "Kaos",
    "tmdb_id": 38164
  },
  {
    "title": "Starman",
    "tmdb_id": 9663
  },
  {
    "title": "Un pesce di nome Wanda",
    "tmdb_id": 623
  },
  {
    "title": "Tucker, un uomo e il suo sogno",
    "tmdb_id": 28176
  },
  {
    "title": "L'uomo dei sogni",
    "tmdb_id": 927010
  },
  {
    "title": "Fuori orario",
    "tmdb_id": 10843
  },
  {
    "title": "Il migliore",
    "tmdb_id": 1111796
  },
  {
    "title": "Brivido caldo",
    "tmdb_id": 14412
  },
  {
    "title": "Interceptor, il guerriero della strada",
    "tmdb_id": 8810
  },
  {
    "title": "L'aereo più pazzo del mondo",
    "tmdb_id": 813
  },
  {
    "title": "Il mio nome è Remo Williams",
    "tmdb_id": 10553
  },
  {
    "title": "Rain man - L'uomo della pioggia",
    "tmdb_id": 380
  },
  {
    "title": "Ladyhawke",
    "tmdb_id": 526
  },
  {
    "title": "L'ultima tentazione di Cristo",
    "tmdb_id": 11051
  },
  {
    "title": "Fandango",
    "tmdb_id": 20348
  },
  {
    "title": "La mosca",
    "tmdb_id": 38125
  },
  {
    "title": "The Killer",
    "tmdb_id": 970347
  },
  {
    "title": "Fa' la cosa giusta",
    "tmdb_id": 925
  },
  {
    "title": "Top Secret!",
    "tmdb_id": 27709
  },
  {
    "title": "Il ritorno dello Jedi",
    "tmdb_id": 1892
  },
  {
    "title": "Il mattino dopo",
    "tmdb_id": 31924
  },
  {
    "title": "Essi Vivono",
    "tmdb_id": 8337
  },
  {
    "title": "Il nome della rosa",
    "tmdb_id": 192
  },
  {
    "title": "La scelta di Sophie",
    "tmdb_id": 15764
  },
  {
    "title": "Tenebre",
    "tmdb_id": 29702
  },
  {
    "title": "La piccola bottega degli orrori",
    "tmdb_id": 10776
  },
  {
    "title": "Quei bravi ragazzi",
    "tmdb_id": 769
  },
  {
    "title": "America Oggi",
    "tmdb_id": 695
  },
  {
    "title": "Casinò",
    "tmdb_id": 524
  },
  {
    "title": "Carlito's Way",
    "tmdb_id": 6075
  },
  {
    "title": "Gli spietati",
    "tmdb_id": 33
  },
  {
    "title": "Nel nome del padre",
    "tmdb_id": 47840
  },
  {
    "title": "L'anguilla",
    "tmdb_id": 20506
  },
  {
    "title": "Lanterne rosse",
    "tmdb_id": 10404
  },
  {
    "title": "Film rosso",
    "tmdb_id": 110
  },
  {
    "title": "La sottile linea rossa",
    "tmdb_id": 8741
  },
  {
    "title": "L'età dell'innocenza",
    "tmdb_id": 10436
  },
  {
    "title": "La bella scontrosa",
    "tmdb_id": 12627
  },
  {
    "title": "Balla coi lupi",
    "tmdb_id": 581
  },
  {
    "title": "In fondo al cuore",
    "tmdb_id": 13819
  },
  {
    "title": "Le ali della libertà",
    "tmdb_id": 278
  },
  {
    "title": "Film blu",
    "tmdb_id": 1104844
  },
  {
    "title": "Mediterraneo",
    "tmdb_id": 38251
  },
  {
    "title": "Braveheart - Cuore impavido",
    "tmdb_id": 197
  },
  {
    "title": "La leggenda del re pescatore",
    "tmdb_id": 177
  },
  {
    "title": "American History X",
    "tmdb_id": 73
  },
  {
    "title": "M. Butterfly",
    "tmdb_id": 1413
  },
  {
    "title": "Summer of Sam - Panico a New York",
    "tmdb_id": 10279
  },
  {
    "title": "Turnè",
    "tmdb_id": 58773
  },
  {
    "title": "Terminator 2 - Il giorno del giudizio",
    "tmdb_id": 280
  },
  {
    "title": "L’esercito delle dodici scimmie",
    "tmdb_id": 63
  },
  {
    "title": "L.A. Confidential",
    "tmdb_id": 2118
  },
  {
    "title": "Le onde del destino",
    "tmdb_id": 145
  },
  {
    "title": "Malcolm X",
    "tmdb_id": 1883
  },
  {
    "title": "Underground",
    "tmdb_id": 17318
  },
  {
    "title": "L’armata delle tenebre",
    "tmdb_id": 766
  },
  {
    "title": "Pulp Fiction",
    "tmdb_id": 680
  },
  {
    "title": "Mezzanotte nel giardino del bene e del male",
    "tmdb_id": 8197
  },
  {
    "title": "JFK - Un caso ancora aperto",
    "tmdb_id": 820
  },
  {
    "title": "La doppia vita di Veronica",
    "tmdb_id": 1600
  },
  {
    "title": "Film bianco",
    "tmdb_id": 109
  },
  {
    "title": "Porco Rosso",
    "tmdb_id": 11621
  },
  {
    "title": "I protagonisti",
    "tmdb_id": 198772
  },
  {
    "title": "The Doors",
    "tmdb_id": 10537
  },
  {
    "title": "Star Trek VI: Rotta verso l’ignoto",
    "tmdb_id": 174
  },
  {
    "title": "Heat - La sfida",
    "tmdb_id": 949
  },
  {
    "title": "Magnolia",
    "tmdb_id": 334
  },
  {
    "title": "Insider - Dietro la verità",
    "tmdb_id": 9008
  },
  {
    "title": "Boogie Nights",
    "tmdb_id": 4995
  },
  {
    "title": "Il cattivo tenente",
    "tmdb_id": 12143
  },
  {
    "title": "Matrix",
    "tmdb_id": 555879
  },
  {
    "title": "Terra e libertà",
    "tmdb_id": 38884
  },
  {
    "title": "Wyatt Earp",
    "tmdb_id": 89888
  },
  {
    "title": "Fino a prova contraria",
    "tmdb_id": 10354
  },
  {
    "title": "Il seme della follia",
    "tmdb_id": 2654
  },
  {
    "title": "Bugsy",
    "tmdb_id": 10337
  },
  {
    "title": "Il postino",
    "tmdb_id": 11010
  },
  {
    "title": "The Commitments",
    "tmdb_id": 11663
  },
  {
    "title": "Ricomincio da capo",
    "tmdb_id": 137
  },
  {
    "title": "Un mondo perfetto",
    "tmdb_id": 9559
  },
  {
    "title": "Paura e delirio a Las Vegas",
    "tmdb_id": 1878
  },
  {
    "title": "Dead Man",
    "tmdb_id": 102362
  },
  {
    "title": "Le iene",
    "tmdb_id": 500
  },
  {
    "title": "La vita a modo mio",
    "tmdb_id": 11593
  },
  {
    "title": "L’ultimo dei mohicani",
    "tmdb_id": 9361
  },
  {
    "title": "La moglie del soldato",
    "tmdb_id": 11386
  },
  {
    "title": "Quiz Show",
    "tmdb_id": 11450
  },
  {
    "title": "Soldi sporchi",
    "tmdb_id": 10223
  },
  {
    "title": "Lupo solitario",
    "tmdb_id": 829294
  },
  {
    "title": "Dead Man Walking",
    "tmdb_id": 687
  },
  {
    "title": "He Got Game",
    "tmdb_id": 9469
  },
  {
    "title": "Hurricane - Il grido dell’innocenza",
    "tmdb_id": 10400
  },
  {
    "title": "Tombstone",
    "tmdb_id": 11969
  },
  {
    "title": "Scream",
    "tmdb_id": 4232
  },
  {
    "title": "L’uomo senza volto",
    "tmdb_id": 210653
  },
  {
    "title": "Il silenzio degli innocenti",
    "tmdb_id": 274
  },
  {
    "title": "Maverick",
    "tmdb_id": 9359
  },
  {
    "title": "Potere assoluto",
    "tmdb_id": 66
  },
  {
    "title": "Once Were Warriors - Una volta erano guerrieri",
    "tmdb_id": 527
  },
  {
    "title": "The Boxer",
    "tmdb_id": 16992
  },
  {
    "title": "Mo’ Better Blues",
    "tmdb_id": 41823
  },
  {
    "title": "U-Turn - Inversione di marcia",
    "tmdb_id": 10155
  },
  {
    "title": "Ancora vivo",
    "tmdb_id": 9333
  },
  {
    "title": "Belli e dannati",
    "tmdb_id": 703134
  },
  {
    "title": "Il grande Lebowski",
    "tmdb_id": 115
  },
  {
    "title": "Gatto nero, gatto bianco",
    "tmdb_id": 1075
  },
  {
    "title": "Lezioni di piano",
    "tmdb_id": 713
  },
  {
    "title": "eXistenZ",
    "tmdb_id": 1946
  },
  {
    "title": "True Lies",
    "tmdb_id": 36955
  },
  {
    "title": "Puerto Escondido",
    "tmdb_id": 46028
  },
  {
    "title": "Il re leone",
    "tmdb_id": 762509
  },
  {
    "title": "I signori della truffa",
    "tmdb_id": 2322
  },
  {
    "title": "Dracula di Bram Stoker",
    "tmdb_id": 6114
  },
  {
    "title": "Qualcosa è cambiato",
    "tmdb_id": 2898
  },
  {
    "title": "Hana-bi",
    "tmdb_id": 5910
  },
  {
    "title": "Schegge di paura",
    "tmdb_id": 1592
  },
  {
    "title": "Tutto su mia madre",
    "tmdb_id": 99
  },
  {
    "title": "Sonatine",
    "tmdb_id": 7500
  },
  {
    "title": "Jumanji",
    "tmdb_id": 8844
  },
  {
    "title": "Donnie Brasco",
    "tmdb_id": 9366
  },
  {
    "title": "Ghost Dog - Il codice del samurai",
    "tmdb_id": 4816
  },
  {
    "title": "Cose preziose",
    "tmdb_id": 10657
  },
  {
    "title": "Strade perdute",
    "tmdb_id": 638
  },
  {
    "title": "Prima dell’alba",
    "tmdb_id": 76
  },
  {
    "title": "L’amante",
    "tmdb_id": 482134
  },
  {
    "title": "Jungle Fever",
    "tmdb_id": 1713
  },
  {
    "title": "Rogue",
    "tmdb_id": 13022
  },
  {
    "title": "Million Dollar Baby",
    "tmdb_id": 70
  },
  {
    "title": "The Betrayed",
    "tmdb_id": 20055
  },
  {
    "title": "Lettere da Iwo Jima",
    "tmdb_id": 1251
  },
  {
    "title": "La 25a ora",
    "tmdb_id": 1429
  },
  {
    "title": "Il petroliere",
    "tmdb_id": 7345
  },
  {
    "title": "Battlestar Galactica (Miniserie TV, 2003)",
    "tmdb_id": 71365
  },
  {
    "title": "Mystic River",
    "tmdb_id": 322
  },
  {
    "title": "Il signore degli anelli - Il ritorno del re",
    "tmdb_id": 122
  },
  {
    "title": "Gran Torino",
    "tmdb_id": 13223
  },
  {
    "title": "Arca russa",
    "tmdb_id": 16646
  },
  {
    "title": "Gangs of New York",
    "tmdb_id": 3131
  },
  {
    "title": "Il signore degli anelli - La compagnia dell'anello",
    "tmdb_id": 120
  },
  {
    "title": "The Departed - Il bene e il male",
    "tmdb_id": 1422
  },
  {
    "title": "Hero",
    "tmdb_id": 360635
  },
  {
    "title": "Changeling",
    "tmdb_id": 3580
  },
  {
    "title": "Comandante",
    "tmdb_id": 1047016
  },
  {
    "title": "Redacted",
    "tmdb_id": 11600
  },
  {
    "title": "Training Day",
    "tmdb_id": 2034
  },
  {
    "title": "Flags of Our Fathers",
    "tmdb_id": 3683
  },
  {
    "title": "Il signore degli anelli - Le due torri",
    "tmdb_id": 121
  },
  {
    "title": "Into the Wild",
    "tmdb_id": 5915
  },
  {
    "title": "Il pianista",
    "tmdb_id": 423
  },
  {
    "title": "Requiem for a Dream",
    "tmdb_id": 641
  },
  {
    "title": "Battlestar Galactica: Razor (Film TV, 2007)",
    "tmdb_id": 69315
  },
  {
    "title": "Bobby",
    "tmdb_id": 10741
  },
  {
    "title": "Lost in La Mancha",
    "tmdb_id": 21189
  },
  {
    "title": "Ogni cosa è illuminata",
    "tmdb_id": 340
  },
  {
    "title": "Chavez - L'ultimo comandante",
    "tmdb_id": 47426
  },
  {
    "title": "Femme Fatale",
    "tmdb_id": 1054495
  },
  {
    "title": "The Door in the Floor",
    "tmdb_id": 1944
  },
  {
    "title": "Il mestiere delle armi",
    "tmdb_id": 56798
  },
  {
    "title": "La tigre e il dragone",
    "tmdb_id": 146
  },
  {
    "title": "Bowling a Columbine",
    "tmdb_id": 1430
  },
  {
    "title": "Crazy Heart",
    "tmdb_id": 25196
  },
  {
    "title": "Frida",
    "tmdb_id": 1360
  },
  {
    "title": "In Bruges - La coscienza dell'assassino",
    "tmdb_id": 8321
  },
  {
    "title": "La promessa dell'assassino (Eastern Promises, 2007)",
    "tmdb_id": 2252
  },
  {
    "title": "Capitalism: A Love Story",
    "tmdb_id": 22074
  },
  {
    "title": "Terra di confine - Open Range",
    "tmdb_id": 2055
  },
  {
    "title": "Inside Man",
    "tmdb_id": 388
  },
  {
    "title": "Pollock",
    "tmdb_id": 12509
  },
  {
    "title": "Le rose del deserto",
    "tmdb_id": 63074
  },
  {
    "title": "La strada per El Dorado",
    "tmdb_id": 10501
  },
  {
    "title": "Cantando dietro i paraventi",
    "tmdb_id": 81697
  },
  {
    "title": "Buongiorno, notte",
    "tmdb_id": 24164
  },
  {
    "title": "San Valentino di sangue in 3D",
    "tmdb_id": 14435
  },
  {
    "title": "Venerdì 13",
    "tmdb_id": 4488
  },
  {
    "title": "Drag Me to Hell",
    "tmdb_id": 16871
  },
  {
    "title": "Gosford Park",
    "tmdb_id": 5279
  },
  {
    "title": "Departures",
    "tmdb_id": 1155752
  },
  {
    "title": "La passione di Cristo",
    "tmdb_id": 615
  },
  {
    "title": "Io non sono qui (I'm Not There, 2007)",
    "tmdb_id": 3902
  },
  {
    "title": "La meglio gioventù",
    "tmdb_id": 11659
  },
  {
    "title": "Apocalypto",
    "tmdb_id": 1579
  },
  {
    "title": "The Mothman Prophecies",
    "tmdb_id": 2637
  },
  {
    "title": "A History of Violence",
    "tmdb_id": 59
  },
  {
    "title": "Tideland",
    "tmdb_id": 11559
  },
  {
    "title": "El Alamein - La linea del fuoco",
    "tmdb_id": 26495
  },
  {
    "title": "I cento passi",
    "tmdb_id": 29458
  },
  {
    "title": "Fearless",
    "tmdb_id": 726664
  },
  {
    "title": "In the Mood for Love",
    "tmdb_id": 843
  },
  {
    "title": "Io non ho paura",
    "tmdb_id": 25300
  },
  {
    "title": "Sicko",
    "tmdb_id": 2359
  },
  {
    "title": "Fahrenheit 9/11",
    "tmdb_id": 532908
  },
  {
    "title": "Collateral",
    "tmdb_id": 1538
  },
  {
    "title": "La foresta dei pugnali volanti (House of Flying Daggers, 2004)",
    "tmdb_id": 9550
  },
  {
    "title": "Operazione Valchiria",
    "tmdb_id": 2253
  },
  {
    "title": "Battle Royale",
    "tmdb_id": 3176
  },
  {
    "title": "Chicago",
    "tmdb_id": 128298
  },
  {
    "title": "Genova",
    "tmdb_id": 12408
  },
  {
    "title": "Il calamaro e la balena (The Squid and the Whale, 2005)",
    "tmdb_id": 10707
  },
  {
    "title": "Mulholland Drive",
    "tmdb_id": 1018
  },
  {
    "title": "Frost/Nixon - Il duello",
    "tmdb_id": 11499
  },
  {
    "title": "La promessa (The Pledge, 2001)",
    "tmdb_id": 5955
  },
  {
    "title": "Lo scafandro e la farfalla (The Diving Bell and the Butterfly, 2007)",
    "tmdb_id": 2013
  },
  {
    "title": "Dolls",
    "tmdb_id": 612592
  },
  {
    "title": "La pianista (The Piano Teacher, 2001)",
    "tmdb_id": 1791
  },
  {
    "title": "La Città di Dio - City of God",
    "tmdb_id": 598
  },
  {
    "title": "Invictus",
    "tmdb_id": 22954
  },
  {
    "title": "La battaglia dei tre regni (Red Cliff? O simile, 2008)",
    "tmdb_id": 12289
  },
  {
    "title": "12",
    "tmdb_id": 739187
  },
  {
    "title": "Il nastro bianco (The White Ribbon, 2009)",
    "tmdb_id": 37903
  },
  {
    "title": "Ferro 3 - La casa vuota (Oldboy? No, Ferro 3, 2004)",
    "tmdb_id": 1280
  },
  {
    "title": "21 Grammi (21 Grams, 2003)",
    "tmdb_id": 470
  },
  {
    "title": "Non è un paese per vecchi (No Country for Old Men, 2007)",
    "tmdb_id": 6977
  },
  {
    "title": "Miami Vice",
    "tmdb_id": 82
  },
  {
    "title": "Parla con lei",
    "tmdb_id": 64
  },
  {
    "title": "Primavera, Estate, Autunno, Inverno... e ancora Primavera",
    "tmdb_id": 113
  },
  {
    "title": "2046",
    "tmdb_id": 844
  },
  {
    "title": "Mare dentro",
    "tmdb_id": 1913
  },
  {
    "title": "Paranoid Park",
    "tmdb_id": 1990
  },
  {
    "title": "Mysterious Skin",
    "tmdb_id": 11171
  },
  {
    "title": "Before Sunset - Prima del tramonto",
    "tmdb_id": 80
  },
  {
    "title": "Il treno per il Darjeeling (The Darjeeling Limited, 2007)",
    "tmdb_id": 4538
  },
  {
    "title": "Inland Empire",
    "tmdb_id": 1730
  },
  {
    "title": "I Tenenbaum (The Royal Tenenbaums, 2001)",
    "tmdb_id": 9428
  },
  {
    "title": "Sweet Sixteen",
    "tmdb_id": 872237
  },
  {
    "title": "A Single Man",
    "tmdb_id": 34653
  },
  {
    "title": "Le tre sepolture (The Three Burials of Melquiades Estrada, 2005)",
    "tmdb_id": 8053
  },
  {
    "title": "Cristalli di memoria",
    "tmdb_id": 660632
  },
  {
    "title": "Bold Pilot - Leggenda di un campione",
    "tmdb_id": 568021
  },
  {
    "title": "Circondati",
    "tmdb_id": 542787
  },
  {
    "title": "Eternal Love",
    "tmdb_id": 468261
  },
  {
    "title": "Elizabeth Harvest",
    "tmdb_id": 457041
  },
  {
    "title": "My Mother",
    "tmdb_id": 701952
  },
  {
    "title": "Abigail",
    "tmdb_id": 648408
  },
  {
    "title": "Verità sepolte",
    "tmdb_id": 257087
  },
  {
    "title": "Mio Figlio",
    "tmdb_id": 692312
  },
  {
    "title": "Bozzetto non troppo",
    "tmdb_id": 415361
  },
  {
    "title": "The Pool",
    "tmdb_id": 11376
  },
  {
    "title": "Intemperie",
    "tmdb_id": 630018
  },
  {
    "title": "Siren",
    "tmdb_id": 195507
  },
  {
    "title": "Mercy",
    "tmdb_id": 1111966
  },
  {
    "title": "Sweetheart",
    "tmdb_id": 463843
  },
  {
    "title": "Cut Off",
    "tmdb_id": 552670
  },
  {
    "title": "Attraction",
    "tmdb_id": 65869
  },
  {
    "title": "The Elevator",
    "tmdb_id": 252954
  },
  {
    "title": "Atto di fede",
    "tmdb_id": 514439
  },
  {
    "title": "Banklady",
    "tmdb_id": 228736
  },
  {
    "title": "La regola delle 3 mogli",
    "tmdb_id": 616257
  },
  {
    "title": "Infidel",
    "tmdb_id": 649401
  },
  {
    "title": "Nomis",
    "tmdb_id": 772758
  },
  {
    "title": "Il corriere - The Mule",
    "tmdb_id": 504172
  },
  {
    "title": "Sulle ali della musica",
    "tmdb_id": 541611
  },
  {
    "title": "Il filo nascosto",
    "tmdb_id": 400617
  },
  {
    "title": "Nebraska",
    "tmdb_id": 129670
  },
  {
    "title": "All Is Lost - Tutto è perduto",
    "tmdb_id": 152747
  },
  {
    "title": "Il corpo della sposa",
    "tmdb_id": 577098
  },
  {
    "title": "Medicus",
    "tmdb_id": 169881
  },
  {
    "title": "Parasite",
    "tmdb_id": 48311
  },
  {
    "title": "Luce",
    "tmdb_id": 492616
  },
  {
    "title": "Attraverso i miei occhi",
    "tmdb_id": 522924
  },
  {
    "title": "Life Like",
    "tmdb_id": 586707
  },
  {
    "title": "4x4",
    "tmdb_id": 575769
  },
  {
    "title": "Marrowbone",
    "tmdb_id": 399366
  },
  {
    "title": "Flatliners - Linea mortale",
    "tmdb_id": 400710
  },
  {
    "title": "The Irishman",
    "tmdb_id": 398978
  },
  {
    "title": "Il labirinto del Grizzly",
    "tmdb_id": 244316
  },
  {
    "title": "Adults in the Room",
    "tmdb_id": 512056
  },
  {
    "title": "Il cammino per Santiago",
    "tmdb_id": 59468
  },
  {
    "title": "La battaglia di Hacksaw Ridge",
    "tmdb_id": 324786
  },
  {
    "title": "Snowden",
    "tmdb_id": 302401
  },
  {
    "title": "The Conspirator",
    "tmdb_id": 60309
  },
  {
    "title": "Faust",
    "tmdb_id": 114242
  },
  {
    "title": "The Blackout - Invasion Heart",
    "tmdb_id": 112710
  },
  {
    "title": "Vivarium",
    "tmdb_id": 458305
  },
  {
    "title": "La vita nascosta - Hidden Life",
    "tmdb_id": 403300
  },
  {
    "title": "Leviathan",
    "tmdb_id": 14372
  },
  {
    "title": "American Sniper",
    "tmdb_id": 190859
  },
  {
    "title": "L'ufficiale e la spia",
    "tmdb_id": 399121
  },
  {
    "title": "Aquaslash",
    "tmdb_id": 607383
  },
  {
    "title": "1918 - I giorni del coraggio",
    "tmdb_id": 438259
  },
  {
    "title": "Roger Waters: Us + Them",
    "tmdb_id": 617924
  },
  {
    "title": "Il professore e il pazzo",
    "tmdb_id": 411728
  },
  {
    "title": "Lincoln",
    "tmdb_id": 340036
  },
  {
    "title": "Snowpiercer",
    "tmdb_id": 110415
  },
  {
    "title": "Western Stars",
    "tmdb_id": 617773
  },
  {
    "title": "Oculus",
    "tmdb_id": 157547
  },
  {
    "title": "Il giovane favoloso",
    "tmdb_id": 283704
  },
  {
    "title": "Torneranno i prati",
    "tmdb_id": 298986
  },
  {
    "title": "Sorry We Missed You",
    "tmdb_id": 522369
  },
  {
    "title": "L'ultimo pastore",
    "tmdb_id": 160219
  },
  {
    "title": "Il traditore",
    "tmdb_id": 575452
  },
  {
    "title": "Io, Daniel Blake",
    "tmdb_id": 374473
  },
  {
    "title": "Hereafter",
    "tmdb_id": 44603
  },
  {
    "title": "Educazione Siberiana",
    "tmdb_id": 171337
  },
  {
    "title": "Hush - il terrore del silenzio",
    "tmdb_id": 376570
  },
  {
    "title": "Anon",
    "tmdb_id": 396806
  },
  {
    "title": "Hell or High Water",
    "tmdb_id": 338766
  },
  {
    "title": "Spider-Man: Un Nuovo Universo",
    "tmdb_id": 324857
  },
  {
    "title": "The Congress",
    "tmdb_id": 1421379
  },
  {
    "title": "Mechanic: Resurrection",
    "tmdb_id": 278924
  },
  {
    "title": "Sulla mia pelle",
    "tmdb_id": 538362
  },
  {
    "title": "Silence",
    "tmdb_id": 68730
  },
  {
    "title": "Old Man & the Gun",
    "tmdb_id": 429203
  },
  {
    "title": "An Invisible Sign",
    "tmdb_id": 59435
  },
  {
    "title": "Il grande e potente Oz",
    "tmdb_id": 68728
  },
  {
    "title": "Hugo Cabret",
    "tmdb_id": 44826
  },
  {
    "title": "Cesare deve morire",
    "tmdb_id": 96821
  },
  {
    "title": "Green Book",
    "tmdb_id": 490132
  },
  {
    "title": "No - I giorni dell'arcobaleno",
    "tmdb_id": 110398
  },
  {
    "title": "Prospect",
    "tmdb_id": 506072
  },
  {
    "title": "Highwaymen - L'ultima Imboscata",
    "tmdb_id": 500682
  },
  {
    "title": "Maleficent: Signora del male",
    "tmdb_id": 420809
  },
  {
    "title": "Bene ma non benissimo",
    "tmdb_id": 581940
  },
  {
    "title": "Les Misérables",
    "tmdb_id": 82695
  },
  {
    "title": "Tre giorni e una vita",
    "tmdb_id": 617986
  },
  {
    "title": "The Tree of Life",
    "tmdb_id": 8967
  },
  {
    "title": "The War - Il pianeta delle scimmie",
    "tmdb_id": 281338
  },
  {
    "title": "Melancholia",
    "tmdb_id": 62215
  },
  {
    "title": "L'uomo nell'ombra",
    "tmdb_id": 3529
  },
  {
    "title": "Lovelace",
    "tmdb_id": 77805
  },
  {
    "title": "The Wolf of Wall Street",
    "tmdb_id": 106646
  },
  {
    "title": "Coco",
    "tmdb_id": 354912
  },
  {
    "title": "The Killer Inside Me",
    "tmdb_id": 37414
  },
  {
    "title": "The Art of the Steal",
    "tmdb_id": 209247
  },
  {
    "title": "La casa di Jack",
    "tmdb_id": 398173
  },
  {
    "title": "The Walk",
    "tmdb_id": 962279
  },
  {
    "title": "Amour",
    "tmdb_id": 86837
  }
]